foliant/preprocessors/elasticsearch.py
foliantcontrib.elasticsearch-1.0.4.dist-info/LICENSE
foliantcontrib.elasticsearch-1.0.4.dist-info/METADATA
foliantcontrib.elasticsearch-1.0.4.dist-info/WHEEL
foliantcontrib.elasticsearch-1.0.4.dist-info/top_level.txt
foliantcontrib.elasticsearch-1.0.4.dist-info/RECORD
