Metadata-Version: 2.1
Name: foliantcontrib.elasticsearch
Version: 1.0.4
Summary: Elasticsearch integration extension for Foliant.
Home-page: https://github.com/foliant-docs/foliantcontrib.elasticsearch
Author: Artemy Lomov
Author-email: artemy@lomov.ru
License: MIT
Platform: any
Classifier: Development Status :: 5 - Production/Stable
Classifier: Environment :: Console
Classifier: Intended Audience :: Developers
Classifier: License :: OSI Approved :: MIT License
Classifier: Operating System :: OS Independent
Classifier: Programming Language :: Python
Classifier: Topic :: Documentation
Classifier: Topic :: Utilities
Requires-Dist: foliant (>=1.0.4)
Requires-Dist: markdown
Requires-Dist: bs4
Requires-Dist: lxml
